denss/__init__.py
denss/_version.py
denss/core.py
denss/options.py
denss/resources/__init__.py
denss/resources/cromer_mann_4gauss.json
denss/resources/cromer_mann_4gauss_offset.json
denss/resources/electrons.json
denss/resources/mean_volumes.json
denss/resources/numH.json
denss/resources/radii_scale_factors.json
denss/resources/resources.py
denss/resources/vdW.json
denss/resources/volH.json
denss/scripts/__init__.py
denss/scripts/denss_abinitio.py
denss/scripts/denss_align.py
denss/scripts/denss_align2xyz.py
denss/scripts/denss_align_and_average.py
denss/scripts/denss_align_by_principal_axes.py
denss/scripts/denss_all.py
denss/scripts/denss_average.py
denss/scripts/denss_calcfsc.py
denss/scripts/denss_fit_data.py
denss/scripts/denss_fsc2res.py
denss/scripts/denss_generate_reference.py
denss/scripts/denss_get_info.py
denss/scripts/denss_hypred2mrc.py
denss/scripts/denss_mrc2sas.py
denss/scripts/denss_mrcops.py
denss/scripts/denss_pdb2mrc.py
denss/scripts/denss_pdb2support.py
denss/scripts/denss_refine.py
denss/scripts/denss_regrid.py
denss/scripts/denss_rho2dat.py
denss/scripts/denss_select_enantiomer.py
denss/scripts/denss_select_enantiomers.py
denss-1.8.7.dist-info/licenses/LICENSE
denss-1.8.7.dist-info/METADATA
denss-1.8.7.dist-info/WHEEL
denss-1.8.7.dist-info/entry_points.txt
denss-1.8.7.dist-info/top_level.txt
denss-1.8.7.dist-info/RECORD
