Metadata-Version: 2.4
Name: denss
Version: 1.8.7
Summary: Calculate electron density from solution scattering data.
Author-email: Thomas Grant <tdgrant@buffalo.edu>
License: GPLv3
Requires-Python: >=3.6
License-File: LICENSE
Requires-Dist: numpy>=1.12.0
Requires-Dist: scipy>=1.0.0
Provides-Extra: plotting
Requires-Dist: matplotlib; extra == "plotting"
Dynamic: license-file
